galib/__init__.py
gaction_lib-0.1a2.dist-info/LICENSE
gaction_lib-0.1a2.dist-info/METADATA
gaction_lib-0.1a2.dist-info/WHEEL
gaction_lib-0.1a2.dist-info/top_level.txt
gaction_lib-0.1a2.dist-info/RECORD
