Metadata-Version: 2.1
Name: gaction-lib
Version: 0.1a2
Summary: [TODO]: Fill your description here
Home-page: UNKNOWN
Author: gawainx
Author-email: liangyixp@live.cn
License: UNKNOWN
Platform: UNKNOWN
Classifier: Programming Language :: Python :: 3.7
Classifier: License :: OSI Approved :: Apache Software License
Classifier: Operating System :: OS Independent
